CHANGES.txt
MANIFEST.in
README.md
setup.py
flask_avro/__init__.py
flask_avro/endpoint.py
flask_avro/exceptions.py
flask_avro/version.py
flask_avro.egg-info/PKG-INFO
flask_avro.egg-info/SOURCES.txt
flask_avro.egg-info/dependency_links.txt
flask_avro.egg-info/not-zip-safe
flask_avro.egg-info/requires.txt
flask_avro.egg-info/top_level.txt
flask_avro/utils/__init__.py
flask_avro/utils/test_client.py
requirements/core.txt
requirements/test.txt