Metadata-Version: 1.1
Name: flask-avro
Version: 0.0.1
Summary: Simple AVRO IPC endpoint registration for Flask
Home-page: https://github.com/packagelib/flask-avro
Author: Jeffrey Starker
Author-email: jstarker@gmail.com
License: Apache License (2.0)
Keywords: flask avro
Platform: UNKNOWN
Classifier: Development Status :: 3 - Alpha
Classifier: Intended Audience :: Developers
Classifier: License :: OSI Approved :: Apache Software License
Classifier: Framework :: Flask
Classifier: Programming Language :: Python :: 2.7
Classifier: Topic :: Internet :: WWW/HTTP
Classifier: Topic :: Software Development :: Libraries :: Python Modules
